odoo/addons/base_currency_iso_4217/README.rst
odoo/addons/base_currency_iso_4217/__init__.py
odoo/addons/base_currency_iso_4217/__manifest__.py
odoo/addons/base_currency_iso_4217/data/res.currency.csv
odoo/addons/base_currency_iso_4217/i18n/base_currency_iso_4217.pot
odoo/addons/base_currency_iso_4217/models/__init__.py
odoo/addons/base_currency_iso_4217/models/res_currency.py
odoo/addons/base_currency_iso_4217/readme/CONTRIBUTORS.rst
odoo/addons/base_currency_iso_4217/readme/DESCRIPTION.rst
odoo/addons/base_currency_iso_4217/static/description/icon.png
odoo/addons/base_currency_iso_4217/static/description/index.html
odoo/addons/base_currency_iso_4217/views/res_currency_views.xml
odoo11_addon_base_currency_iso_4217-11.0.1.0.1.dist-info/METADATA
odoo11_addon_base_currency_iso_4217-11.0.1.0.1.dist-info/WHEEL
odoo11_addon_base_currency_iso_4217-11.0.1.0.1.dist-info/top_level.txt
odoo11_addon_base_currency_iso_4217-11.0.1.0.1.dist-info/RECORD
